{
  "$schema": "https://raw.githubusercontent.com/spdx/spdx-spec/v2.2.1/schemas/spdx-schema.json",
  "spdxVersion": "SPDX-2.2",
  "dataLicense": "CC0-1.0",
  "SPDXID": "SPDXRef-DOCUMENT",
  "documentNamespace": "https://spdx.org/spdxdocs/sdl2-image-x64-mingw-dynamic-2.8.8#2-b98f02a0-4ca7-4547-a8a6-30ba9efb3bbe",
  "name": "sdl2-image:x64-mingw-dynamic@2.8.8#2 740ffd574085a6641c0d9a412bf749c19e913fc3b729d57b14334ff93043858a",
  "creationInfo": {
    "creators": [
      "Tool: vcpkg-2025-09-03-4580816534ed8fd9634ac83d46471440edd82dfe"
    ],
    "created": "2025-11-12T18:52:22Z"
  },
  "relationships": [
    {
      "spdxElementId": "SPDXRef-port",
      "relationshipType": "GENERATES",
      "relatedSpdxElement": "SPDXRef-binary"
    },
    {
      "spdxElementId": "SPDXRef-port",
      "relationshipType": "CONTAINS",
      "relatedSpdxElement": "SPDXRef-port-file-0"
    },
    {
      "spdxElementId": "SPDXRef-port",
      "relationshipType": "CONTAINS",
      "relatedSpdxElement": "SPDXRef-port-file-1"
    },
    {
      "spdxElementId": "SPDXRef-port",
      "relationshipType": "CONTAINS",
      "relatedSpdxElement": "SPDXRef-port-file-2"
    },
    {
      "spdxElementId": "SPDXRef-port",
      "relationshipType": "CONTAINS",
      "relatedSpdxElement": "SPDXRef-port-file-3"
    },
    {
      "spdxElementId": "SPDXRef-port-file-3",
      "relationshipType": "DEPENDENCY_MANIFEST_OF",
      "relatedSpdxElement": "SPDXRef-port"
    },
    {
      "spdxElementId": "SPDXRef-binary",
      "relationshipType": "CONTAINS",
      "relatedSpdxElement": "SPDXRef-binary-file-0"
    },
    {
      "spdxElementId": "SPDXRef-binary",
      "relationshipType": "CONTAINS",
      "relatedSpdxElement": "SPDXRef-binary-file-1"
    },
    {
      "spdxElementId": "SPDXRef-binary",
      "relationshipType": "CONTAINS",
      "relatedSpdxElement": "SPDXRef-binary-file-2"
    },
    {
      "spdxElementId": "SPDXRef-binary",
      "relationshipType": "CONTAINS",
      "relatedSpdxElement": "SPDXRef-binary-file-3"
    },
    {
      "spdxElementId": "SPDXRef-binary",
      "relationshipType": "CONTAINS",
      "relatedSpdxElement": "SPDXRef-binary-file-4"
    },
    {
      "spdxElementId": "SPDXRef-binary",
      "relationshipType": "CONTAINS",
      "relatedSpdxElement": "SPDXRef-binary-file-5"
    },
    {
      "spdxElementId": "SPDXRef-binary",
      "relationshipType": "CONTAINS",
      "relatedSpdxElement": "SPDXRef-binary-file-6"
    },
    {
      "spdxElementId": "SPDXRef-binary",
      "relationshipType": "CONTAINS",
      "relatedSpdxElement": "SPDXRef-binary-file-7"
    },
    {
      "spdxElementId": "SPDXRef-binary",
      "relationshipType": "CONTAINS",
      "relatedSpdxElement": "SPDXRef-binary-file-8"
    },
    {
      "spdxElementId": "SPDXRef-binary",
      "relationshipType": "CONTAINS",
      "relatedSpdxElement": "SPDXRef-binary-file-9"
    },
    {
      "spdxElementId": "SPDXRef-binary",
      "relationshipType": "CONTAINS",
      "relatedSpdxElement": "SPDXRef-binary-file-10"
    },
    {
      "spdxElementId": "SPDXRef-binary",
      "relationshipType": "CONTAINS",
      "relatedSpdxElement": "SPDXRef-binary-file-11"
    },
    {
      "spdxElementId": "SPDXRef-binary",
      "relationshipType": "CONTAINS",
      "relatedSpdxElement": "SPDXRef-binary-file-12"
    },
    {
      "spdxElementId": "SPDXRef-binary",
      "relationshipType": "CONTAINS",
      "relatedSpdxElement": "SPDXRef-binary-file-13"
    },
    {
      "spdxElementId": "SPDXRef-binary",
      "relationshipType": "CONTAINS",
      "relatedSpdxElement": "SPDXRef-binary-file-14"
    },
    {
      "spdxElementId": "SPDXRef-binary",
      "relationshipType": "CONTAINS",
      "relatedSpdxElement": "SPDXRef-binary-file-15"
    },
    {
      "spdxElementId": "SPDXRef-binary",
      "relationshipType": "CONTAINS",
      "relatedSpdxElement": "SPDXRef-binary-file-16"
    },
    {
      "spdxElementId": "SPDXRef-binary",
      "relationshipType": "CONTAINS",
      "relatedSpdxElement": "SPDXRef-binary-file-17"
    }
  ],
  "packages": [
    {
      "name": "sdl2-image",
      "SPDXID": "SPDXRef-port",
      "versionInfo": "2.8.8#2",
      "downloadLocation": "git+https://github.com/Microsoft/vcpkg@3e390ce4c736f698cd4e670d27fd9bca4185d047",
      "homepage": "https://github.com/libsdl-org/SDL_image",
      "licenseConcluded": "Zlib",
      "licenseDeclared": "NOASSERTION",
      "copyrightText": "NOASSERTION",
      "description": "SDL_image is an image file loading library. It loads images as SDL surfaces and textures, and supports the following formats: BMP, GIF, JPEG, LBM, PCX, PNG, PNM, TGA, TIFF, WEBP, XCF, XPM, XV",
      "comment": "This is the port (recipe) consumed by vcpkg."
    },
    {
      "name": "sdl2-image:x64-mingw-dynamic",
      "SPDXID": "SPDXRef-binary",
      "versionInfo": "740ffd574085a6641c0d9a412bf749c19e913fc3b729d57b14334ff93043858a",
      "downloadLocation": "NONE",
      "licenseConcluded": "Zlib",
      "licenseDeclared": "NOASSERTION",
      "copyrightText": "NOASSERTION",
      "comment": "This is a binary package built by vcpkg."
    },
    {
      "SPDXID": "SPDXRef-resource-0",
      "name": "libsdl-org/SDL_image",
      "downloadLocation": "git+https://github.com/libsdl-org/SDL_image@release-2.8.8",
      "licenseConcluded": "NOASSERTION",
      "licenseDeclared": "NOASSERTION",
      "copyrightText": "NOASSERTION",
      "checksums": [
        {
          "algorithm": "SHA512",
          "checksumValue": "3fef846eb0ad51a8b346bb421c87eb81f0e2f186d700a219ebf17146397da404b3683853322989ed939b1672cc36b799582f24bc58a0393fc6c698a65cda2b82"
        }
      ]
    }
  ],
  "files": [
    {
      "fileName": "./fix-findwebp.patch",
      "SPDXID": "SPDXRef-port-file-0",
      "checksums": [
        {
          "algorithm": "SHA256",
          "checksumValue": "6ae1538331c1bb5ef84a70dce382ce4a118db764314f8049fb229c99c57c0873"
        }
      ],
      "licenseConcluded": "NOASSERTION",
      "copyrightText": "NOASSERTION"
    },
    {
      "fileName": "./portfile.cmake",
      "SPDXID": "SPDXRef-port-file-1",
      "checksums": [
        {
          "algorithm": "SHA256",
          "checksumValue": "ad13b119ed7c0809855d08694e698997c4304f0be075ffe3bf49285cec148d79"
        }
      ],
      "licenseConcluded": "NOASSERTION",
      "copyrightText": "NOASSERTION"
    },
    {
      "fileName": "./usage",
      "SPDXID": "SPDXRef-port-file-2",
      "checksums": [
        {
          "algorithm": "SHA256",
          "checksumValue": "d78ce4ac61e158f4a5056753dd2bd7e3b11e7ded1f10a36c8e749029940e651f"
        }
      ],
      "licenseConcluded": "NOASSERTION",
      "copyrightText": "NOASSERTION"
    },
    {
      "fileName": "./vcpkg.json",
      "SPDXID": "SPDXRef-port-file-3",
      "checksums": [
        {
          "algorithm": "SHA256",
          "checksumValue": "11bb97de9c5d72f566c55970075267803f2002927d7ef596f289dba8e5554058"
        }
      ],
      "licenseConcluded": "NOASSERTION",
      "copyrightText": "NOASSERTION"
    },
    {
      "fileName": "./bin/SDL2_image.dll",
      "SPDXID": "SPDXRef-binary-file-0",
      "checksums": [
        {
          "algorithm": "SHA256",
          "checksumValue": "1793e867ada57ab265885f3a8caa709cab6b1f97759c06f10e2650d835080289"
        }
      ],
      "licenseConcluded": "NOASSERTION",
      "copyrightText": "NOASSERTION"
    },
    {
      "fileName": "./BUILD_INFO",
      "SPDXID": "SPDXRef-binary-file-1",
      "checksums": [
        {
          "algorithm": "SHA256",
          "checksumValue": "6ab53fb9a3c8a8fd7267dfe9da42066bcaebbb691a450ba4a83145564fe9c597"
        }
      ],
      "licenseConcluded": "NOASSERTION",
      "copyrightText": "NOASSERTION"
    },
    {
      "fileName": "./debug/bin/SDL2_imaged.dll",
      "SPDXID": "SPDXRef-binary-file-2",
      "checksums": [
        {
          "algorithm": "SHA256",
          "checksumValue": "e74cde40ce764ee0e0bfb49f280a8fddc44e86a60a7017f4774116e418db85be"
        }
      ],
      "licenseConcluded": "NOASSERTION",
      "copyrightText": "NOASSERTION"
    },
    {
      "fileName": "./debug/lib/libSDL2_imaged.dll.a",
      "SPDXID": "SPDXRef-binary-file-3",
      "checksums": [
        {
          "algorithm": "SHA256",
          "checksumValue": "a5f5a865e943284ee49c7fd20e9a0ce11dbe98af614b8a866fe835e881a79813"
        }
      ],
      "licenseConcluded": "NOASSERTION",
      "copyrightText": "NOASSERTION"
    },
    {
      "fileName": "./debug/lib/pkgconfig/SDL2_image.pc",
      "SPDXID": "SPDXRef-binary-file-4",
      "checksums": [
        {
          "algorithm": "SHA256",
          "checksumValue": "5feeedd7033ec4c97d4e5288f8edf855f45f521db3e1369ae391cdf8de168af9"
        }
      ],
      "licenseConcluded": "NOASSERTION",
      "copyrightText": "NOASSERTION"
    },
    {
      "fileName": "./include/SDL2/SDL_image.h",
      "SPDXID": "SPDXRef-binary-file-5",
      "checksums": [
        {
          "algorithm": "SHA256",
          "checksumValue": "9e864e900579058f69bf83940723a333fc87f638aad93e2c4ce8549fff46c11b"
        }
      ],
      "licenseConcluded": "NOASSERTION",
      "copyrightText": "NOASSERTION"
    },
    {
      "fileName": "./lib/libSDL2_image.dll.a",
      "SPDXID": "SPDXRef-binary-file-6",
      "checksums": [
        {
          "algorithm": "SHA256",
          "checksumValue": "c4bb045a87905b515a8164f7d91e140dd294e5179090c22853c67206cc4b4e8b"
        }
      ],
      "licenseConcluded": "NOASSERTION",
      "copyrightText": "NOASSERTION"
    },
    {
      "fileName": "./lib/pkgconfig/SDL2_image.pc",
      "SPDXID": "SPDXRef-binary-file-7",
      "checksums": [
        {
          "algorithm": "SHA256",
          "checksumValue": "0562987d7146f950bd5a0fae7e397c06caaa44d31c27f0ee51ec616c345c35ac"
        }
      ],
      "licenseConcluded": "NOASSERTION",
      "copyrightText": "NOASSERTION"
    },
    {
      "fileName": "./share/licenses/SDL2_image/LICENSE.txt",
      "SPDXID": "SPDXRef-binary-file-8",
      "checksums": [
        {
          "algorithm": "SHA256",
          "checksumValue": "7826eca0a0f7e591f38dd844e207a200aac81a59b20d8a30c3af8c6282af13e6"
        }
      ],
      "licenseConcluded": "NOASSERTION",
      "copyrightText": "NOASSERTION"
    },
    {
      "fileName": "./share/sdl2-image/copyright",
      "SPDXID": "SPDXRef-binary-file-9",
      "checksums": [
        {
          "algorithm": "SHA256",
          "checksumValue": "7826eca0a0f7e591f38dd844e207a200aac81a59b20d8a30c3af8c6282af13e6"
        }
      ],
      "licenseConcluded": "NOASSERTION",
      "copyrightText": "NOASSERTION"
    },
    {
      "fileName": "./share/sdl2-image/usage",
      "SPDXID": "SPDXRef-binary-file-10",
      "checksums": [
        {
          "algorithm": "SHA256",
          "checksumValue": "d78ce4ac61e158f4a5056753dd2bd7e3b11e7ded1f10a36c8e749029940e651f"
        }
      ],
      "licenseConcluded": "NOASSERTION",
      "copyrightText": "NOASSERTION"
    },
    {
      "fileName": "./share/SDL2_image/Findlibjxl.cmake",
      "SPDXID": "SPDXRef-binary-file-11",
      "checksums": [
        {
          "algorithm": "SHA256",
          "checksumValue": "d9a9bd88c45446ee87ca6993852b637c3e48bb66dfa1d7c27ffa09e79278b8d5"
        }
      ],
      "licenseConcluded": "NOASSERTION",
      "copyrightText": "NOASSERTION"
    },
    {
      "fileName": "./share/SDL2_image/Findwebp.cmake",
      "SPDXID": "SPDXRef-binary-file-12",
      "checksums": [
        {
          "algorithm": "SHA256",
          "checksumValue": "cf9ee614cbf3cd2da619deccfeda0a9a8b27461c99efe7e2099e154fc02934d4"
        }
      ],
      "licenseConcluded": "NOASSERTION",
      "copyrightText": "NOASSERTION"
    },
    {
      "fileName": "./share/SDL2_image/SDL2_image-shared-targets-debug.cmake",
      "SPDXID": "SPDXRef-binary-file-13",
      "checksums": [
        {
          "algorithm": "SHA256",
          "checksumValue": "d5028128a56a47c0df6b6c1203058ba9e730cc8d06fa19bc0887ddf9463a3f85"
        }
      ],
      "licenseConcluded": "NOASSERTION",
      "copyrightText": "NOASSERTION"
    },
    {
      "fileName": "./share/SDL2_image/SDL2_image-shared-targets-release.cmake",
      "SPDXID": "SPDXRef-binary-file-14",
      "checksums": [
        {
          "algorithm": "SHA256",
          "checksumValue": "3d7c2a0024f67007d55dfdf577fdb6e0b519b6848ab7eafb2dd55c33463cf2ee"
        }
      ],
      "licenseConcluded": "NOASSERTION",
      "copyrightText": "NOASSERTION"
    },
    {
      "fileName": "./share/SDL2_image/SDL2_image-shared-targets.cmake",
      "SPDXID": "SPDXRef-binary-file-15",
      "checksums": [
        {
          "algorithm": "SHA256",
          "checksumValue": "2f5ff458fb71828a7fb3544056d15cad631050a12833312ceb27fde706800791"
        }
      ],
      "licenseConcluded": "NOASSERTION",
      "copyrightText": "NOASSERTION"
    },
    {
      "fileName": "./share/SDL2_image/SDL2_imageConfig.cmake",
      "SPDXID": "SPDXRef-binary-file-16",
      "checksums": [
        {
          "algorithm": "SHA256",
          "checksumValue": "938a7a311cac779b23ac3bfd349d06a8a663f4876c6f15b8511211f2ee4ee2f2"
        }
      ],
      "licenseConcluded": "NOASSERTION",
      "copyrightText": "NOASSERTION"
    },
    {
      "fileName": "./share/SDL2_image/SDL2_imageConfigVersion.cmake",
      "SPDXID": "SPDXRef-binary-file-17",
      "checksums": [
        {
          "algorithm": "SHA256",
          "checksumValue": "46c053a53f664807515e504aeb6b91090bf6c02a40255100b9d59fc15489d0ed"
        }
      ],
      "licenseConcluded": "NOASSERTION",
      "copyrightText": "NOASSERTION"
    }
  ]
}
